swarm/__init__.py
swarm/core.py
swarm/types.py
swarm/util.py
swarm/repl/__init__.py
swarm/repl/repl.py
agentsys_swarm-0.1.2.dist-info/METADATA
agentsys_swarm-0.1.2.dist-info/WHEEL
agentsys_swarm-0.1.2.dist-info/licenses/LICENSE
agentsys_swarm-0.1.2.dist-info/RECORD
