Metadata-Version: 2.3
Name: agentsys-swarm
Version: 0.1.2
Summary: A lightweight, stateless multi-agent orchestration framework
Project-URL: Homepage, https://github.com/lifsys/agentsys-swarm
Project-URL: Repository, https://github.com/lifsys/agentsys-swarm.git
Project-URL: Documentation, https://github.com/lifsys/agentsys-swarm#readme
Project-URL: Issues, https://github.com/lifsys/agentsys-swarm/issues
Author: OpenAI Solutions
License: MIT License
Classifier: Development Status :: 3 - Alpha
Classifier: Intended Audience :: Developers
Classifier: License :: OSI Approved :: MIT License
Classifier: Operating System :: OS Independent
Classifier: Programming Language :: Python :: 3
Classifier: Programming Language :: Python :: 3.10
Classifier: Programming Language :: Python :: 3.11
Requires-Python: >=3.10
Requires-Dist: instructor
Requires-Dist: numpy
Requires-Dist: openai>=1.33.0
Requires-Dist: pydantic>=2.0.0
Requires-Dist: python-dotenv>=0.19.0
Requires-Dist: requests
Requires-Dist: tqdm
Requires-Dist: typing-extensions>=4.0.0
Provides-Extra: dev
Requires-Dist: black>=22.0; extra == 'dev'
Requires-Dist: isort>=5.0; extra == 'dev'
Requires-Dist: mypy>=0.9; extra == 'dev'
Requires-Dist: pre-commit; extra == 'dev'
Requires-Dist: pytest>=7.0; extra == 'dev'
